AlgorithmicAspectsOfMachineLearningMit18409/README.md
AlgorithmicAspectsOfMachineLearningMit18409/__init__.py
AlgorithmicAspectsOfMachineLearningMit18409/__main__.py
AlgorithmicAspectsOfMachineLearningMit18409/file.pdf
AlgorithmicAspectsOfMachineLearningMit18409/index.html
algorithmic_aspects_of_machine_learning_mit_18_409-2024.3.1.0.dist-info/METADATA
algorithmic_aspects_of_machine_learning_mit_18_409-2024.3.1.0.dist-info/WHEEL
algorithmic_aspects_of_machine_learning_mit_18_409-2024.3.1.0.dist-info/entry_points.txt
algorithmic_aspects_of_machine_learning_mit_18_409-2024.3.1.0.dist-info/top_level.txt
algorithmic_aspects_of_machine_learning_mit_18_409-2024.3.1.0.dist-info/RECORD
